thsrobotsdk/__init__.py
thsrobotsdk/client.py
thsrobotsdk/exceptions.py
thsrobotsdk-0.2.dist-info/METADATA
thsrobotsdk-0.2.dist-info/WHEEL
thsrobotsdk-0.2.dist-info/top_level.txt
thsrobotsdk-0.2.dist-info/RECORD
