Metadata-Version: 2.4
Name: thsrobotsdk
Version: 0.2
Summary: A Python SDK for the Thsrobot API
Home-page: https://github.com/your-repo-url
Author: linagzxx
Author-email: Your Name <your.email@example.com>
Project-URL: Homepage, https://github.com/yourusername/thsrobotsdk
Project-URL: Bug Tracker, https://github.com/yourusername/thsrobotsdk/issues
Keywords: thsrobot,sdk
Classifier: Programming Language :: Python :: 3
Classifier: License :: OSI Approved :: MIT License
Classifier: Operating System :: OS Independent
Requires-Dist: requests
Dynamic: author
Dynamic: home-page
